foodfactslib/__init__.py
foodfactslib/foodfacts.py
Foodfacts-0.1.dist-info/METADATA
Foodfacts-0.1.dist-info/WHEEL
Foodfacts-0.1.dist-info/top_level.txt
Foodfacts-0.1.dist-info/RECORD
